skyblockparser/__init__.py
skyblockparser/auctionhouse.py
skyblockparser/constants.py
skyblockparser/exceptions.py
skyblockparser/levels.py
skyblockparser/pets.py
skyblockparser/profile.py
skyblockparser/renderer.py
skyblockparser/fonts/Minecraft-Italic.otf
skyblockparser/fonts/MinecraftBold.otf
skyblockparser/fonts/MinecraftBoldItalic.otf
skyblockparser/fonts/MinecraftItalic.otf
skyblockparser/fonts/MinecraftRegular.otf
skyblockparser/fonts/unifont.ttf
skyblockparser-2.0.dist-info/METADATA
skyblockparser-2.0.dist-info/WHEEL
skyblockparser-2.0.dist-info/top_level.txt
skyblockparser-2.0.dist-info/RECORD
