Metadata-Version: 2.1
Name: skyblockparser
Version: 2.0
Summary: A package allowing you to parse skyblock profile information including networth.
Author: nom
Author-email: nom <noemtdev@gmail.com>
Project-URL: Homepage, https://github.com/noemtdev/skyblockparser
Project-URL: Bug Tracker, https://github.com/noemtdev/skyblockparser/issues
Keywords: python,hypixel,skyblock,hypixel skyblock
Classifier: Programming Language :: Python :: 3
Classifier: License :: OSI Approved :: MIT License
Classifier: Operating System :: OS Independent
Requires-Python: >=3.7
Requires-Dist: aiohttp
Requires-Dist: pillow
